README.md
setup.py
whatsappstract/__init__.py
whatsappstract/__main__.py
whatsappstract/osd2futils.py
whatsappstract/whatsapp.py
whatsappstract.egg-info/PKG-INFO
whatsappstract.egg-info/SOURCES.txt
whatsappstract.egg-info/dependency_links.txt
whatsappstract.egg-info/requires.txt
whatsappstract.egg-info/top_level.txt