Metadata-Version: 2.1
Name: whatsappstract
Version: 0.0.5
Summary: Allow user to extract URLS from whatsapp messages
Home-page: https://github.com/ccs-amsterdam/whatsappstract
Author: Felicia Loecherbach, Damian Trilling, Wouter van Atteveldt
Author-email: wouter.van.atteveldt@vu.nl
License: UNKNOWN
Platform: UNKNOWN
Classifier: Programming Language :: Python :: 3
Classifier: License :: OSI Approved :: MIT License
Classifier: Operating System :: OS Independent
Requires-Python: >=3.6
